graphtorch/__init__.py
graphtorch/matrix.py
graphtorch/model.py
graphtorch/neat_graphtorch.py
graphtorch-0.1.dist-info/METADATA
graphtorch-0.1.dist-info/WHEEL
graphtorch-0.1.dist-info/top_level.txt
graphtorch-0.1.dist-info/RECORD
